setup.py
display/__init__.py
display/gfx.py
display/lazy.py
display/ssd1306.py
display/st7735r.py
display/write.py
display/examples/example0.py
display/examples/example1.py
display/examples/example2.py
display/examples/example3.py
display/examples/example4.py
display/examples/example5.py
display/fonts/__init__.py
display/fonts/bookerly_12.py
display/fonts/bookerly_15.py
display/fonts/bookerly_20.py
display/fonts/gen.py
display/fonts/press_start_2p_12.py
display/fonts/press_start_2p_15.py
display/fonts/press_start_2p_20.py
display/fonts/ubuntu_12.py
display/fonts/ubuntu_15.py
display/fonts/ubuntu_20.py
display/fonts/ubuntu_condensed_12.py
display/fonts/ubuntu_condensed_15.py
display/fonts/ubuntu_condensed_20.py
display/fonts/ubuntu_mono_12.py
display/fonts/ubuntu_mono_15.py
display/fonts/ubuntu_mono_20.py
micropython_display.egg-info/PKG-INFO
micropython_display.egg-info/SOURCES.txt
micropython_display.egg-info/dependency_links.txt
micropython_display.egg-info/top_level.txt