Metadata-Version: 1.2
Name: micropython-display
Version: 1.15
Summary: Micropython scripts for use displays.
Home-page: http://yeisoncardona.com/
Author: Yeison Cardona
Author-email: yeisoneng@gmail.com
Maintainer: Yeison Cardona
Maintainer-email: yeisoneng@gmail.com
License: GNU GPL
Download-URL: https://bitbucket.org/espressoide/micropython-display/downloads/
Platform: UNKNOWN
